horseracepredictor/__init__.py
horseracepredictor/predictor.py
horseracepredictor-0.3.7.dist-info/METADATA
horseracepredictor-0.3.7.dist-info/WHEEL
horseracepredictor-0.3.7.dist-info/top_level.txt
horseracepredictor-0.3.7.dist-info/RECORD
